ai4science/__init__.py
ai4science/core.py
ai4science-0.1.0.dist-info/licenses/LICENSE
ai4science-0.1.0.dist-info/METADATA
ai4science-0.1.0.dist-info/WHEEL
ai4science-0.1.0.dist-info/top_level.txt
ai4science-0.1.0.dist-info/RECORD
