Metadata-Version: 2.4
Name: ai4science
Version: 0.1.0
Summary: Tools for AI for Science
Author-email: Your Name <you@example.com>
Project-URL: Homepage, https://github.com/yourname/ai4science
Project-URL: Issues, https://github.com/yourname/ai4science/issues
Keywords: ai4science,ai,science
Classifier: Programming Language :: Python :: 3
Classifier: License :: OSI Approved :: MIT License
Classifier: Operating System :: OS Independent
Requires-Python: >=3.9
License-File: LICENSE
Dynamic: license-file
